{"shapes": [{"points": [[410, 181], [443, 203]], "shape_type": "rectangle", "group_id": null, "label": "Tree", "flags": {}}, {"points": [[443, 423], [474, 447]], "shape_type": "rectangle", "group_id": null, "label": "Tree", "flags": {}}, {"points": [[102, 180], [135, 203]], "shape_type": "rectangle", "group_id": null, "label": "Tree", "flags": {}}, {"points": [[322, 284], [354, 308]], "shape_type": "rectangle", "group_id": null, "label": "Tree", "flags": {}}, {"points": [[152, 319], [186, 343]], "shape_type": "rectangle", "group_id": null, "label": "Tree", "flags": {}}, {"points": [[492, 373], [512, 395]], "shape_type": "rectangle", "group_id": null, "label": "Tree", "flags": {}}, {"points": [[463, 275], [497, 299]], "shape_type": "rectangle", "group_id": null, "label": "Tree", "flags": {}}, {"points": [[322, 86], [353, 108]], "shape_type": "rectangle", "group_id": null, "label": "Tree", "flags": {}}, {"points": [[96, 410], [133, 434]], "shape_type": "rectangle", "group_id": null, "label": "Tree", "flags": {}}, {"points": [[323, 446], [354, 468]], "shape_type": "rectangle", "group_id": null, "label": "Tree", "flags": {}}, {"points": [[61, 463], [100, 485]], "shape_type": "rectangle", "group_id": null, "label": "Tree", "flags": {}}, {"points": [[168, 412], [200, 435]], "shape_type": "rectangle", "group_id": null, "label": "Tree", "flags": {}}, {"points": [[356, 215], [388, 236]], "shape_type": "rectangle", "group_id": null, "label": "Tree", "flags": {}}, {"points": [[206, 258], [240, 283]], "shape_type": "rectangle", "group_id": null, "label": "Tree", "flags": {}}, {"points": [[0, 244], [14, 263]], "shape_type": "rectangle", "group_id": null, "label": "Tree", "flags": {}}, {"points": [[265, 165], [306, 193]], "shape_type": "rectangle", "group_id": null, "label": "Tree", "flags": {}}, {"points": [[61, 346], [111, 369]], "shape_type": "rectangle", "group_id": null, "label": "Tree", "flags": {}}, {"points": [[99, 243], [145, 270]], "shape_type": "rectangle", "group_id": null, "label": "Tree", "flags": {}}, {"points": [[205, 121], [232, 142]], "shape_type": "rectangle", "group_id": null, "label": "Tree", "flags": {}}, {"points": [[149, 183], [176, 203]], "shape_type": "rectangle", "group_id": null, "label": "Tree", "flags": {}}, {"points": [[220, 355], [249, 373]], "shape_type": "rectangle", "group_id": null, "label": "Tree", "flags": {}}, {"points": [[8, 129], [55, 159]], "shape_type": "rectangle", "group_id": null, "label": "Tree", "flags": {}}, {"points": [[493, 222], [512, 252]], "shape_type": "rectangle", "group_id": null, "label": "Tree", "flags": {}}, {"points": [[418, 126], [442, 146]], "shape_type": "rectangle", "group_id": null, "label": "Tree", "flags": {}}, {"points": [[488, 129], [512, 160]], "shape_type": "rectangle", "group_id": null, "label": "Tree", "flags": {}}, {"points": [[463, 275], [497, 299]], "shape_type": "rectangle", "group_id": null, "label": "Tree", "flags": {}}, {"points": [[96, 410], [133, 434]], "shape_type": "rectangle", "group_id": null, "label": "Tree", "flags": {}}, {"points": [[152, 319], [186, 343]], "shape_type": "rectangle", "group_id": null, "label": "Tree", "flags": {}}, {"points": [[61, 463], [100, 485]], "shape_type": "rectangle", "group_id": null, "label": "Tree", "flags": {}}, {"points": [[410, 181], [443, 203]], "shape_type": "rectangle", "group_id": null, "label": "Tree", "flags": {}}, {"points": [[443, 423], [474, 447]], "shape_type": "rectangle", "group_id": null, "label": "Tree", "flags": {}}, {"points": [[102, 180], [135, 203]], "shape_type": "rectangle", "group_id": null, "label": "Tree", "flags": {}}, {"points": [[322, 284], [354, 308]], "shape_type": "rectangle", "group_id": null, "label": "Tree", "flags": {}}, {"points": [[206, 258], [240, 283]], "shape_type": "rectangle", "group_id": null, "label": "Tree", "flags": {}}, {"points": [[492, 373], [512, 395]], "shape_type": "rectangle", "group_id": null, "label": "Tree", "flags": {}}, {"points": [[322, 86], [353, 108]], "shape_type": "rectangle", "group_id": null, "label": "Tree", "flags": {}}, {"points": [[265, 165], [306, 193]], "shape_type": "rectangle", "group_id": null, "label": "Tree", "flags": {}}, {"points": [[99, 243], [145, 270]], "shape_type": "rectangle", "group_id": null, "label": "Tree", "flags": {}}, {"points": [[61, 346], [111, 369]], "shape_type": "rectangle", "group_id": null, "label": "Tree", "flags": {}}, {"points": [[323, 446], [354, 468]], "shape_type": "rectangle", "group_id": null, "label": "Tree", "flags": {}}, {"points": [[356, 215], [388, 236]], "shape_type": "rectangle", "group_id": null, "label": "Tree", "flags": {}}, {"points": [[168, 412], [200, 435]], "shape_type": "rectangle", "group_id": null, "label": "Tree", "flags": {}}, {"points": [[8, 129], [55, 159]], "shape_type": "rectangle", "group_id": null, "label": "Tree", "flags": {}}, {"points": [[0, 244], [14, 263]], "shape_type": "rectangle", "group_id": null, "label": "Tree", "flags": {}}, {"points": [[493, 222], [512, 252]], "shape_type": "rectangle", "group_id": null, "label": "Tree", "flags": {}}, {"points": [[205, 121], [232, 142]], "shape_type": "rectangle", "group_id": null, "label": "Tree", "flags": {}}, {"points": [[488, 129], [512, 160]], "shape_type": "rectangle", "group_id": null, "label": "Tree", "flags": {}}, {"points": [[149, 183], [176, 203]], "shape_type": "rectangle", "group_id": null, "label": "Tree", "flags": {}}, {"points": [[220, 355], [249, 373]], "shape_type": "rectangle", "group_id": null, "label": "Tree", "flags": {}}, {"points": [[418, 126], [442, 146]], "shape_type": "rectangle", "group_id": null, "label": "Tree", "flags": {}}, {"points": [[63, 268], [98, 307]], "shape_type": "rectangle", "group_id": null, "label": "Tree", "flags": {}}, {"points": [[53, 304], [67, 317]], "shape_type": "rectangle", "group_id": null, "label": "Tree", "flags": {}}, {"points": [[463, 275], [497, 299]], "shape_type": "rectangle", "group_id": null, "label": "Tree", "flags": {}}, {"points": [[96, 410], [133, 434]], "shape_type": "rectangle", "group_id": null, "label": "Tree", "flags": {}}, {"points": [[152, 319], [186, 343]], "shape_type": "rectangle", "group_id": null, "label": "Tree", "flags": {}}, {"points": [[61, 463], [100, 485]], "shape_type": "rectangle", "group_id": null, "label": "Tree", "flags": {}}, {"points": [[410, 181], [443, 203]], "shape_type": "rectangle", "group_id": null, "label": "Tree", "flags": {}}, {"points": [[443, 423], [474, 447]], "shape_type": "rectangle", "group_id": null, "label": "Tree", "flags": {}}, {"points": [[102, 180], [135, 203]], "shape_type": "rectangle", "group_id": null, "label": "Tree", "flags": {}}, {"points": [[322, 284], [354, 308]], "shape_type": "rectangle", "group_id": null, "label": "Tree", "flags": {}}, {"points": [[206, 258], [240, 283]], "shape_type": "rectangle", "group_id": null, "label": "Tree", "flags": {}}, {"points": [[492, 373], [512, 395]], "shape_type": "rectangle", "group_id": null, "label": "Tree", "flags": {}}, {"points": [[322, 86], [353, 108]], "shape_type": "rectangle", "group_id": null, "label": "Tree", "flags": {}}, {"points": [[265, 165], [306, 193]], "shape_type": "rectangle", "group_id": null, "label": "Tree", "flags": {}}, {"points": [[99, 243], [145, 270]], "shape_type": "rectangle", "group_id": null, "label": "Tree", "flags": {}}, {"points": [[61, 346], [111, 369]], "shape_type": "rectangle", "group_id": null, "label": "Tree", "flags": {}}, {"points": [[323, 446], [354, 468]], "shape_type": "rectangle", "group_id": null, "label": "Tree", "flags": {}}, {"points": [[356, 215], [388, 236]], "shape_type": "rectangle", "group_id": null, "label": "Tree", "flags": {}}, {"points": [[168, 412], [200, 435]], "shape_type": "rectangle", "group_id": null, "label": "Tree", "flags": {}}, {"points": [[8, 129], [55, 159]], "shape_type": "rectangle", "group_id": null, "label": "Tree", "flags": {}}, {"points": [[0, 244], [14, 263]], "shape_type": "rectangle", "group_id": null, "label": "Tree", "flags": {}}, {"points": [[493, 222], [512, 252]], "shape_type": "rectangle", "group_id": null, "label": "Tree", "flags": {}}, {"points": [[205, 121], [232, 142]], "shape_type": "rectangle", "group_id": null, "label": "Tree", "flags": {}}, {"points": [[488, 129], [512, 160]], "shape_type": "rectangle", "group_id": null, "label": "Tree", "flags": {}}, {"points": [[149, 183], [176, 203]], "shape_type": "rectangle", "group_id": null, "label": "Tree", "flags": {}}, {"points": [[220, 355], [249, 373]], "shape_type": "rectangle", "group_id": null, "label": "Tree", "flags": {}}, {"points": [[418, 126], [442, 146]], "shape_type": "rectangle", "group_id": null, "label": "Tree", "flags": {}}, {"points": [[63, 268], [98, 307]], "shape_type": "rectangle", "group_id": null, "label": "Tree", "flags": {}}, {"points": [[53, 304], [67, 317]], "shape_type": "rectangle", "group_id": null, "label": "Tree", "flags": {}}, {"points": [[463, 275], [497, 299]], "shape_type": "rectangle", "group_id": null, "label": "Tree", "flags": {}}, {"points": [[96, 410], [133, 434]], "shape_type": "rectangle", "group_id": null, "label": "Tree", "flags": {}}, {"points": [[152, 319], [186, 343]], "shape_type": "rectangle", "group_id": null, "label": "Tree", "flags": {}}, {"points": [[61, 463], [100, 485]], "shape_type": "rectangle", "group_id": null, "label": "Tree", "flags": {}}, {"points": [[410, 181], [443, 203]], "shape_type": "rectangle", "group_id": null, "label": "Tree", "flags": {}}, {"points": [[443, 423], [474, 447]], "shape_type": "rectangle", "group_id": null, "label": "Tree", "flags": {}}, {"points": [[102, 180], [135, 203]], "shape_type": "rectangle", "group_id": null, "label": "Tree", "flags": {}}, {"points": [[322, 284], [354, 308]], "shape_type": "rectangle", "group_id": null, "label": "Tree", "flags": {}}, {"points": [[206, 258], [240, 283]], "shape_type": "rectangle", "group_id": null, "label": "Tree", "flags": {}}, {"points": [[492, 373], [512, 395]], "shape_type": "rectangle", "group_id": null, "label": "Tree", "flags": {}}, {"points": [[322, 86], [353, 108]], "shape_type": "rectangle", "group_id": null, "label": "Tree", "flags": {}}, {"points": [[265, 165], [306, 193]], "shape_type": "rectangle", "group_id": null, "label": "Tree", "flags": {}}, {"points": [[99, 243], [145, 270]], "shape_type": "rectangle", "group_id": null, "label": "Tree", "flags": {}}, {"points": [[61, 346], [111, 369]], "shape_type": "rectangle", "group_id": null, "label": "Tree", "flags": {}}, {"points": [[323, 446], [354, 468]], "shape_type": "rectangle", "group_id": null, "label": "Tree", "flags": {}}, {"points": [[356, 215], [388, 236]], "shape_type": "rectangle", "group_id": null, "label": "Tree", "flags": {}}, {"points": [[168, 412], [200, 435]], "shape_type": "rectangle", "group_id": null, "label": "Tree", "flags": {}}, {"points": [[8, 129], [55, 159]], "shape_type": "rectangle", "group_id": null, "label": "Tree", "flags": {}}, {"points": [[0, 244], [14, 263]], "shape_type": "rectangle", "group_id": null, "label": "Tree", "flags": {}}, {"points": [[493, 222], [512, 252]], "shape_type": "rectangle", "group_id": null, "label": "Tree", "flags": {}}, {"points": [[205, 121], [232, 142]], "shape_type": "rectangle", "group_id": null, "label": "Tree", "flags": {}}, {"points": [[488, 129], [512, 160]], "shape_type": "rectangle", "group_id": null, "label": "Tree", "flags": {}}, {"points": [[149, 183], [176, 203]], "shape_type": "rectangle", "group_id": null, "label": "Tree", "flags": {}}, {"points": [[220, 355], [249, 373]], "shape_type": "rectangle", "group_id": null, "label": "Tree", "flags": {}}, {"points": [[418, 126], [442, 146]], "shape_type": "rectangle", "group_id": null, "label": "Tree", "flags": {}}, {"points": [[63, 268], [98, 307]], "shape_type": "rectangle", "group_id": null, "label": "Tree", "flags": {}}, {"points": [[53, 304], [67, 317]], "shape_type": "rectangle", "group_id": null, "label": "Tree", "flags": {}}, {"points": [[463, 275], [497, 299]], "shape_type": "rectangle", "group_id": null, "label": "Tree", "flags": {}}, {"points": [[96, 410], [133, 434]], "shape_type": "rectangle", "group_id": null, "label": "Tree", "flags": {}}, {"points": [[61, 463], [100, 485]], "shape_type": "rectangle", "group_id": null, "label": "Tree", "flags": {}}, {"points": [[152, 319], [186, 343]], "shape_type": "rectangle", "group_id": null, "label": "Tree", "flags": {}}, {"points": [[410, 181], [443, 203]], "shape_type": "rectangle", "group_id": null, "label": "Tree", "flags": {}}, {"points": [[443, 423], [474, 447]], "shape_type": "rectangle", "group_id": null, "label": "Tree", "flags": {}}, {"points": [[206, 258], [240, 283]], "shape_type": "rectangle", "group_id": null, "label": "Tree", "flags": {}}, {"points": [[102, 180], [135, 203]], "shape_type": "rectangle", "group_id": null, "label": "Tree", "flags": {}}, {"points": [[322, 284], [354, 308]], "shape_type": "rectangle", "group_id": null, "label": "Tree", "flags": {}}, {"points": [[492, 373], [512, 395]], "shape_type": "rectangle", "group_id": null, "label": "Tree", "flags": {}}, {"points": [[265, 165], [306, 193]], "shape_type": "rectangle", "group_id": null, "label": "Tree", "flags": {}}, {"points": [[322, 86], [353, 108]], "shape_type": "rectangle", "group_id": null, "label": "Tree", "flags": {}}, {"points": [[99, 243], [145, 270]], "shape_type": "rectangle", "group_id": null, "label": "Tree", "flags": {}}, {"points": [[61, 346], [111, 369]], "shape_type": "rectangle", "group_id": null, "label": "Tree", "flags": {}}, {"points": [[323, 446], [354, 468]], "shape_type": "rectangle", "group_id": null, "label": "Tree", "flags": {}}, {"points": [[8, 129], [55, 159]], "shape_type": "rectangle", "group_id": null, "label": "Tree", "flags": {}}, {"points": [[356, 215], [388, 236]], "shape_type": "rectangle", "group_id": null, "label": "Tree", "flags": {}}, {"points": [[168, 412], [200, 435]], "shape_type": "rectangle", "group_id": null, "label": "Tree", "flags": {}}, {"points": [[493, 222], [512, 252]], "shape_type": "rectangle", "group_id": null, "label": "Tree", "flags": {}}, {"points": [[0, 244], [14, 263]], "shape_type": "rectangle", "group_id": null, "label": "Tree", "flags": {}}, {"points": [[488, 129], [512, 160]], "shape_type": "rectangle", "group_id": null, "label": "Tree", "flags": {}}, {"points": [[205, 121], [232, 142]], "shape_type": "rectangle", "group_id": null, "label": "Tree", "flags": {}}, {"points": [[149, 183], [176, 203]], "shape_type": "rectangle", "group_id": null, "label": "Tree", "flags": {}}, {"points": [[220, 355], [249, 373]], "shape_type": "rectangle", "group_id": null, "label": "Tree", "flags": {}}, {"points": [[418, 126], [442, 146]], "shape_type": "rectangle", "group_id": null, "label": "Tree", "flags": {}}, {"points": [[63, 268], [98, 307]], "shape_type": "rectangle", "group_id": null, "label": "Tree", "flags": {}}]}