{"shapes": [{"points": [[169, 496], [199, 512]], "shape_type": "rectangle", "group_id": null, "label": "Tree", "flags": {}}, {"points": [[341, 0], [374, 18]], "shape_type": "rectangle", "group_id": null, "label": "Tree", "flags": {}}, {"points": [[323, 404], [388, 439]], "shape_type": "rectangle", "group_id": null, "label": "Tree", "flags": {}}, {"points": [[272, 16], [301, 36]], "shape_type": "rectangle", "group_id": null, "label": "Tree", "flags": {}}, {"points": [[14, 139], [58, 169]], "shape_type": "rectangle", "group_id": null, "label": "Tree", "flags": {}}, {"points": [[456, 400], [502, 429]], "shape_type": "rectangle", "group_id": null, "label": "Tree", "flags": {}}, {"points": [[416, 113], [443, 131]], "shape_type": "rectangle", "group_id": null, "label": "Tree", "flags": {}}, {"points": [[204, 127], [252, 156]], "shape_type": "rectangle", "group_id": null, "label": "Tree", "flags": {}}, {"points": [[140, 433], [168, 450]], "shape_type": "rectangle", "group_id": null, "label": "Tree", "flags": {}}, {"points": [[104, 104], [157, 132]], "shape_type": "rectangle", "group_id": null, "label": "Tree", "flags": {}}, {"points": [[418, 499], [465, 512]], "shape_type": "rectangle", "group_id": null, "label": "Tree", "flags": {}}, {"points": [[169, 496], [199, 512]], "shape_type": "rectangle", "group_id": null, "label": "Tree", "flags": {}}, {"points": [[341, 0], [374, 18]], "shape_type": "rectangle", "group_id": null, "label": "Tree", "flags": {}}, {"points": [[14, 139], [58, 169]], "shape_type": "rectangle", "group_id": null, "label": "Tree", "flags": {}}, {"points": [[331, 403], [378, 430]], "shape_type": "rectangle", "group_id": null, "label": "Tree", "flags": {}}, {"points": [[456, 400], [502, 429]], "shape_type": "rectangle", "group_id": null, "label": "Tree", "flags": {}}, {"points": [[204, 127], [252, 156]], "shape_type": "rectangle", "group_id": null, "label": "Tree", "flags": {}}, {"points": [[104, 104], [157, 132]], "shape_type": "rectangle", "group_id": null, "label": "Tree", "flags": {}}, {"points": [[272, 16], [301, 36]], "shape_type": "rectangle", "group_id": null, "label": "Tree", "flags": {}}, {"points": [[418, 499], [465, 512]], "shape_type": "rectangle", "group_id": null, "label": "Tree", "flags": {}}, {"points": [[416, 113], [443, 131]], "shape_type": "rectangle", "group_id": null, "label": "Tree", "flags": {}}, {"points": [[140, 433], [168, 450]], "shape_type": "rectangle", "group_id": null, "label": "Tree", "flags": {}}, {"points": [[169, 496], [199, 512]], "shape_type": "rectangle", "group_id": null, "label": "Tree", "flags": {}}, {"points": [[341, 0], [374, 18]], "shape_type": "rectangle", "group_id": null, "label": "Tree", "flags": {}}, {"points": [[14, 139], [58, 169]], "shape_type": "rectangle", "group_id": null, "label": "Tree", "flags": {}}, {"points": [[331, 403], [378, 430]], "shape_type": "rectangle", "group_id": null, "label": "Tree", "flags": {}}, {"points": [[456, 400], [502, 429]], "shape_type": "rectangle", "group_id": null, "label": "Tree", "flags": {}}, {"points": [[204, 127], [252, 156]], "shape_type": "rectangle", "group_id": null, "label": "Tree", "flags": {}}, {"points": [[104, 104], [157, 132]], "shape_type": "rectangle", "group_id": null, "label": "Tree", "flags": {}}, {"points": [[272, 16], [301, 36]], "shape_type": "rectangle", "group_id": null, "label": "Tree", "flags": {}}, {"points": [[418, 499], [465, 512]], "shape_type": "rectangle", "group_id": null, "label": "Tree", "flags": {}}, {"points": [[416, 113], [443, 131]], "shape_type": "rectangle", "group_id": null, "label": "Tree", "flags": {}}, {"points": [[140, 433], [168, 450]], "shape_type": "rectangle", "group_id": null, "label": "Tree", "flags": {}}, {"points": [[169, 496], [199, 512]], "shape_type": "rectangle", "group_id": null, "label": "Tree", "flags": {}}, {"points": [[341, 0], [374, 18]], "shape_type": "rectangle", "group_id": null, "label": "Tree", "flags": {}}, {"points": [[14, 139], [58, 169]], "shape_type": "rectangle", "group_id": null, "label": "Tree", "flags": {}}, {"points": [[331, 403], [378, 430]], "shape_type": "rectangle", "group_id": null, "label": "Tree", "flags": {}}, {"points": [[456, 400], [502, 429]], "shape_type": "rectangle", "group_id": null, "label": "Tree", "flags": {}}, {"points": [[204, 127], [252, 156]], "shape_type": "rectangle", "group_id": null, "label": "Tree", "flags": {}}, {"points": [[104, 104], [157, 132]], "shape_type": "rectangle", "group_id": null, "label": "Tree", "flags": {}}, {"points": [[272, 16], [301, 36]], "shape_type": "rectangle", "group_id": null, "label": "Tree", "flags": {}}, {"points": [[418, 499], [465, 512]], "shape_type": "rectangle", "group_id": null, "label": "Tree", "flags": {}}, {"points": [[416, 113], [443, 131]], "shape_type": "rectangle", "group_id": null, "label": "Tree", "flags": {}}, {"points": [[140, 433], [168, 450]], "shape_type": "rectangle", "group_id": null, "label": "Tree", "flags": {}}, {"points": [[14, 139], [58, 169]], "shape_type": "rectangle", "group_id": null, "label": "Tree", "flags": {}}, {"points": [[331, 403], [378, 430]], "shape_type": "rectangle", "group_id": null, "label": "Tree", "flags": {}}, {"points": [[456, 400], [502, 429]], "shape_type": "rectangle", "group_id": null, "label": "Tree", "flags": {}}, {"points": [[169, 496], [199, 512]], "shape_type": "rectangle", "group_id": null, "label": "Tree", "flags": {}}, {"points": [[341, 0], [374, 18]], "shape_type": "rectangle", "group_id": null, "label": "Tree", "flags": {}}, {"points": [[204, 127], [252, 156]], "shape_type": "rectangle", "group_id": null, "label": "Tree", "flags": {}}, {"points": [[104, 104], [157, 132]], "shape_type": "rectangle", "group_id": null, "label": "Tree", "flags": {}}, {"points": [[272, 16], [301, 36]], "shape_type": "rectangle", "group_id": null, "label": "Tree", "flags": {}}, {"points": [[418, 499], [465, 512]], "shape_type": "rectangle", "group_id": null, "label": "Tree", "flags": {}}, {"points": [[416, 113], [443, 131]], "shape_type": "rectangle", "group_id": null, "label": "Tree", "flags": {}}, {"points": [[140, 433], [168, 450]], "shape_type": "rectangle", "group_id": null, "label": "Tree", "flags": {}}]}